Metadata-Version: 2.4
Name: digamma-ep
Version: 1.3.1
Summary: Symbolic audit framework with CZVS, curvature zones, and compliance logic
Home-page: https://github.com/Cerene-Salt/Digamma-Prime-Framework
Author: Cerene Salt
Author-email: Cesar <your@email.com>
License: MIT
Project-URL: Homepage, https://github.com/Cerene-Salt/Digamma-Prime-Framework
Project-URL: Documentation, https://github.com/Cerene-Salt/Digamma-Prime-Framework/wiki
Project-URL: Source, https://github.com/Cerene-Salt/Digamma-Prime-Framework
Keywords: symbolic audit,CZVS,compliance,curvature,semantic drift,badge logic
Requires-Python: >=3.11
Requires-Dist: numpy
Requires-Dist: sympy
Requires-Dist: matplotlib
Requires-Dist: scipy
Requires-Dist: fastapi
Requires-Dist: streamlit
Requires-Dist: psycopg2-binary
Dynamic: author
Dynamic: home-page
Dynamic: requires-python
